gac/__init__.py
gac/__version__.py
gac/ai.py
gac/ai_utils.py
gac/auth_cli.py
gac/cli.py
gac/commit_executor.py
gac/config.py
gac/config_cli.py
gac/diff_cli.py
gac/errors.py
gac/git.py
gac/git_state_validator.py
gac/grouped_commit_workflow.py
gac/init_cli.py
gac/interactive_mode.py
gac/language_cli.py
gac/main.py
gac/model_cli.py
gac/model_identifier.py
gac/oauth_retry.py
gac/postprocess.py
gac/preprocess.py
gac/prompt.py
gac/prompt_builder.py
gac/prompt_cli.py
gac/py.typed
gac/security.py
gac/utils.py
gac/workflow_context.py
gac/workflow_utils.py
gac/constants/__init__.py
gac/constants/commit.py
gac/constants/defaults.py
gac/constants/file_patterns.py
gac/constants/languages.py
gac/oauth/__init__.py
gac/oauth/claude_code.py
gac/oauth/qwen_oauth.py
gac/oauth/token_store.py
gac/providers/README.md
gac/providers/__init__.py
gac/providers/anthropic.py
gac/providers/azure_openai.py
gac/providers/base.py
gac/providers/cerebras.py
gac/providers/chutes.py
gac/providers/claude_code.py
gac/providers/custom_anthropic.py
gac/providers/custom_openai.py
gac/providers/deepseek.py
gac/providers/error_handler.py
gac/providers/fireworks.py
gac/providers/gemini.py
gac/providers/groq.py
gac/providers/kimi_coding.py
gac/providers/lmstudio.py
gac/providers/minimax.py
gac/providers/mistral.py
gac/providers/moonshot.py
gac/providers/ollama.py
gac/providers/openai.py
gac/providers/openrouter.py
gac/providers/protocol.py
gac/providers/qwen.py
gac/providers/registry.py
gac/providers/replicate.py
gac/providers/streamlake.py
gac/providers/synthetic.py
gac/providers/together.py
gac/providers/zai.py
gac/templates/__init__.py
gac/templates/question_generation.txt
gac/templates/system_prompt.txt
gac/templates/user_prompt.txt
gac-3.12.1.dist-info/METADATA
gac-3.12.1.dist-info/WHEEL
gac-3.12.1.dist-info/entry_points.txt
gac-3.12.1.dist-info/licenses/LICENSE
gac-3.12.1.dist-info/RECORD
