Metadata-Version: 2.4
Name: gac
Version: 3.12.1
Summary: LLM-powered Git commit message generator with multi-provider support
Project-URL: Homepage, https://github.com/cellwebb/gac
Project-URL: Documentation, https://github.com/cellwebb/gac#readme
Project-URL: Repository, https://github.com/cellwebb/gac.git
Project-URL: Issues, https://github.com/cellwebb/gac/issues
Project-URL: Changelog, https://github.com/cellwebb/gac/blob/main/CHANGELOG.md
Project-URL: Source, https://github.com/cellwebb/gac
Author-email: cellwebb <cellwebb@users.noreply.github.com>
License-Expression: MIT
License-File: LICENSE
Classifier: Development Status :: 4 - Beta
Classifier: Programming Language :: Python
Classifier: Programming Language :: Python :: 3.10
Classifier: Programming Language :: Python :: 3.11
Classifier: Programming Language :: Python :: 3.12
Classifier: Programming Language :: Python :: 3.13
Classifier: Programming Language :: Python :: 3.14
Classifier: Programming Language :: Python :: Implementation :: CPython
Classifier: Programming Language :: Python :: Implementation :: PyPy
Requires-Python: >=3.10
Requires-Dist: click>=8.3.0
Requires-Dist: httpcore>=1.0.9
Requires-Dist: httpx>=0.28.0
Requires-Dist: prompt-toolkit>=3.0.36
Requires-Dist: pydantic>=2.12.0
Requires-Dist: python-dotenv>=1.1.1
Requires-Dist: questionary
Requires-Dist: rich>=14.1.0
Provides-Extra: dev
Requires-Dist: build; extra == 'dev'
Requires-Dist: codecov; extra == 'dev'
Requires-Dist: pytest; extra == 'dev'
Requires-Dist: pytest-cov; extra == 'dev'
Requires-Dist: ruff; extra == 'dev'
Requires-Dist: twine; extra == 'dev'
